{
  "$schema": "https://developer.microsoft.com/json-schemas/fabric/item/report/definition/visualContainer/2.9.0/schema.json",
  "name": "32936fda2e11b276b50b",
  "position": {
    "x": 970,
    "y": 80,
    "z": 1187,
    "height": 455,
    "width": 940,
    "tabOrder": 500
  },
  "visual": {
    "visualType": "columnChart",
    "query": {
      "queryState": {
        "Category": {
          "projections": [
            {
              "field": {
                "Column": {
                  "Expression": {
                    "SourceRef": {
                      "Entity": "Date"
                    }
                  },
                  "Property": "Date"
                }
              },
              "queryRef": "Date.Date",
              "nativeQueryRef": "Date",
              "active": true
            },
            {
              "field": {
                "Column": {
                  "Expression": {
                    "SourceRef": {
                      "Entity": "Time"
                    }
                  },
                  "Property": "Hour"
                }
              },
              "queryRef": "Time.Hour",
              "nativeQueryRef": "Hour",
              "active": false
            },
            {
              "field": {
                "Column": {
                  "Expression": {
                    "SourceRef": {
                      "Entity": "Time"
                    }
                  },
                  "Property": "Minute"
                }
              },
              "queryRef": "Time.Minute",
              "nativeQueryRef": "Minute",
              "active": false
            }
          ]
        },
        "Series": {
          "projections": [
            {
              "field": {
                "Column": {
                  "Expression": {
                    "SourceRef": {
                      "Entity": "Connection info"
                    }
                  },
                  "Property": "Auth. type"
                }
              },
              "queryRef": "Connection info.Auth. type",
              "nativeQueryRef": "Auth. type"
            }
          ]
        },
        "Y": {
          "projections": [
            {
              "field": {
                "Measure": {
                  "Expression": {
                    "SourceRef": {
                      "Entity": "_Measures"
                    }
                  },
                  "Property": "Max connections - Connections"
                }
              },
              "queryRef": "_Measures.Max connections - Connections",
              "nativeQueryRef": "Max connections",
              "displayName": "Max connections"
            }
          ]
        }
      },
      "sortDefinition": {
        "sort": [
          {
            "field": {
              "Column": {
                "Expression": {
                  "SourceRef": {
                    "Entity": "Date"
                  }
                },
                "Property": "Date"
              }
            },
            "direction": "Ascending"
          },
          {
            "field": {
              "Column": {
                "Expression": {
                  "SourceRef": {
                    "Entity": "Time"
                  }
                },
                "Property": "Hour"
              }
            },
            "direction": "Ascending"
          }
        ]
      }
    },
    "objects": {
      "labels": [
        {
          "properties": {
            "labelDisplayUnits": {
              "expr": {
                "Literal": {
                  "Value": "1D"
                }
              }
            }
          }
        }
      ]
    },
    "visualContainerObjects": {
      "title": [
        {
          "properties": {
            "text": {
              "expr": {
                "Literal": {
                  "Value": "'Connections'"
                }
              }
            }
          }
        }
      ],
      "subTitle": [
        {
          "properties": {
            "text": {
              "expr": {
                "Literal": {
                  "Value": "''"
                }
              }
            },
            "show": {
              "expr": {
                "Literal": {
                  "Value": "false"
                }
              }
            }
          }
        }
      ]
    },
    "drillFilterOtherVisuals": true
  },
  "filterConfig": {
    "filters": [
      {
        "name": "23b9237fd622b50402ce",
        "field": {
          "Column": {
            "Expression": {
              "SourceRef": {
                "Entity": "Date"
              }
            },
            "Property": "Date"
          }
        },
        "type": "Categorical"
      },
      {
        "name": "a6770597561231056010",
        "field": {
          "Column": {
            "Expression": {
              "SourceRef": {
                "Entity": "Time"
              }
            },
            "Property": "Hour"
          }
        },
        "type": "Advanced"
      },
      {
        "name": "131580169e5bc315a36a",
        "field": {
          "Column": {
            "Expression": {
              "SourceRef": {
                "Entity": "Time"
              }
            },
            "Property": "Minute"
          }
        },
        "type": "Advanced"
      },
      {
        "name": "bb6a936ee74d155b42ab",
        "field": {
          "Column": {
            "Expression": {
              "SourceRef": {
                "Entity": "Connection info"
              }
            },
            "Property": "Auth. type"
          }
        },
        "type": "Categorical"
      },
      {
        "name": "8cc93e11370411ed4058",
        "field": {
          "Measure": {
            "Expression": {
              "SourceRef": {
                "Entity": "_Measures"
              }
            },
            "Property": "Max connections - Connections"
          }
        },
        "type": "Advanced"
      }
    ]
  }
}