{
  "$schema": "https://developer.microsoft.com/json-schemas/fabric/item/report/definition/visualContainer/2.9.0/schema.json",
  "name": "cd6154533424c0c0e07e",
  "position": {
    "x": 1670,
    "y": 80,
    "z": 8000,
    "height": 80,
    "width": 220,
    "tabOrder": 3000
  },
  "visual": {
    "visualType": "slicer",
    "query": {
      "queryState": {
        "Values": {
          "projections": [
            {
              "field": {
                "Column": {
                  "Expression": {
                    "SourceRef": {
                      "Entity": "Date"
                    }
                  },
                  "Property": "Year"
                }
              },
              "queryRef": "Date.Year",
              "nativeQueryRef": "Year",
              "active": true
            }
          ]
        }
      }
    },
    "objects": {
      "general": [
        {
          "properties": {}
        }
      ],
      "data": [
        {
          "properties": {}
        }
      ]
    },
    "visualContainerObjects": {
      "title": [
        {
          "properties": {
            "text": {
              "expr": {
                "Literal": {
                  "Value": "'Year Slicer'"
                }
              }
            }
          }
        }
      ]
    },
    "drillFilterOtherVisuals": true
  },
  "parentGroupName": "64b272bda274da8725db",
  "filterConfig": {
    "filters": [
      {
        "name": "23e683a0031ce0076eaa",
        "field": {
          "Column": {
            "Expression": {
              "SourceRef": {
                "Entity": "Date"
              }
            },
            "Property": "Year"
          }
        },
        "type": "Advanced"
      },
      {
        "name": "62c205836a424e009ad4",
        "field": {
          "Measure": {
            "Expression": {
              "SourceRef": {
                "Entity": "_Measures"
              }
            },
            "Property": "VLF Filter - Log shipping status"
          }
        },
        "type": "Advanced",
        "filter": {
          "Version": 2,
          "From": [
            {
              "Name": "_",
              "Entity": "_Measures",
              "Type": 0
            }
          ],
          "Where": [
            {
              "Condition": {
                "Not": {
                  "Expression": {
                    "Comparison": {
                      "ComparisonKind": 0,
                      "Left": {
                        "Measure": {
                          "Expression": {
                            "SourceRef": {
                              "Source": "_"
                            }
                          },
                          "Property": "VLF Filter - Log shipping status"
                        }
                      },
                      "Right": {
                        "Literal": {
                          "Value": "null"
                        }
                      }
                    }
                  }
                }
              }
            }
          ]
        },
        "howCreated": "User"
      }
    ]
  }
}