{
  "$schema": "https://developer.microsoft.com/json-schemas/fabric/item/report/definition/visualContainer/2.1.0/schema.json",
  "name": "7b33a148ec49b9f993c8",
  "position": {
    "x": 10,
    "y": 750,
    "z": 1500,
    "height": 270,
    "width": 1900,
    "tabOrder": 9000
  },
  "visual": {
    "visualType": "tableEx",
    "query": {
      "queryState": {
        "Values": {
          "projections": [
            {
              "field": {
                "Column": {
                  "Expression": {
                    "SourceRef": {
                      "Entity": "Database"
                    }
                  },
                  "Property": "Database - Drill-through for Configuration history"
                }
              },
              "queryRef": "Database.Database - Drill-through for Configuration history",
              "nativeQueryRef": "Database",
              "displayName": "Database"
            },
            {
              "field": {
                "Column": {
                  "Expression": {
                    "SourceRef": {
                      "Entity": "Database scoped configuration"
                    }
                  },
                  "Property": "Key"
                }
              },
              "queryRef": "Database scoped configuration.Key1",
              "nativeQueryRef": "Key1"
            },
            {
              "field": {
                "Column": {
                  "Expression": {
                    "SourceRef": {
                      "Entity": "Database scoped configurations"
                    }
                  },
                  "Property": "Value"
                }
              },
              "queryRef": "Database scoped configuration.Value",
              "nativeQueryRef": "Value"
            },
            {
              "field": {
                "Column": {
                  "Expression": {
                    "SourceRef": {
                      "Entity": "Database scoped configurations"
                    }
                  },
                  "Property": "Value for secondary"
                }
              },
              "queryRef": "Database scoped configurations.Value for secondary",
              "nativeQueryRef": "Value for secondary"
            },
            {
              "field": {
                "Column": {
                  "Expression": {
                    "SourceRef": {
                      "Entity": "Database scoped configurations"
                    }
                  },
                  "Property": "DefaultIndicator"
                }
              },
              "queryRef": "Database scoped configuration.DefaultIndicator",
              "nativeQueryRef": "Def. flag",
              "displayName": "Def. flag"
            },
            {
              "field": {
                "Column": {
                  "Expression": {
                    "SourceRef": {
                      "Entity": "Database scoped configurations"
                    }
                  },
                  "Property": "Timestamp"
                }
              },
              "queryRef": "Database scoped configuration.Timestamp",
              "nativeQueryRef": "Timestamp"
            },
            {
              "field": {
                "Column": {
                  "Expression": {
                    "SourceRef": {
                      "Entity": "Database scoped configurations"
                    }
                  },
                  "Property": "ConfigurationSortOrder"
                }
              },
              "queryRef": "Database scoped configuration.ConfigurationSortOrder",
              "nativeQueryRef": "Sort order",
              "displayName": "Sort order"
            }
          ]
        }
      },
      "sortDefinition": {
        "sort": [
          {
            "field": {
              "Column": {
                "Expression": {
                  "SourceRef": {
                    "Entity": "Database scoped configurations"
                  }
                },
                "Property": "ConfigurationSortOrder"
              }
            },
            "direction": "Ascending"
          }
        ]
      }
    },
    "objects": {
      "total": [
        {
          "properties": {
            "totals": {
              "expr": {
                "Literal": {
                  "Value": "false"
                }
              }
            }
          }
        }
      ],
      "columnFormatting": [
        {
          "properties": {
            "alignment": {
              "expr": {
                "Literal": {
                  "Value": "'Center'"
                }
              }
            }
          },
          "selector": {
            "metadata": "Database scoped configuration.DefaultIndicator"
          }
        }
      ]
    },
    "visualContainerObjects": {
      "title": [
        {
          "properties": {
            "text": {
              "expr": {
                "Measure": {
                  "Expression": {
                    "SourceRef": {
                      "Entity": "_Measures"
                    }
                  },
                  "Property": "Title DSC - Database configuration"
                }
              }
            },
            "show": {
              "expr": {
                "Literal": {
                  "Value": "true"
                }
              }
            }
          }
        }
      ],
      "visualTooltip": [
        {
          "properties": {
            "show": {
              "expr": {
                "Literal": {
                  "Value": "false"
                }
              }
            },
            "section": {
              "expr": {
                "Literal": {
                  "Value": "'___AUTO___'"
                }
              }
            }
          }
        }
      ]
    },
    "drillFilterOtherVisuals": true
  },
  "filterConfig": {
    "filters": [
      {
        "name": "cef79a5f6009b89dba12",
        "field": {
          "Measure": {
            "Expression": {
              "SourceRef": {
                "Entity": "_Measures"
              }
            },
            "Property": "VLF - Database configuration"
          }
        },
        "type": "Advanced",
        "filter": {
          "Version": 2,
          "From": [
            {
              "Name": "_",
              "Entity": "_Measures",
              "Type": 0
            }
          ],
          "Where": [
            {
              "Condition": {
                "Not": {
                  "Expression": {
                    "Comparison": {
                      "ComparisonKind": 0,
                      "Left": {
                        "Measure": {
                          "Expression": {
                            "SourceRef": {
                              "Source": "_"
                            }
                          },
                          "Property": "VLF - Database configuration"
                        }
                      },
                      "Right": {
                        "Literal": {
                          "Value": "null"
                        }
                      }
                    }
                  }
                }
              }
            }
          ]
        },
        "howCreated": "User"
      }
    ]
  }
}