{
  "$schema": "https://developer.microsoft.com/json-schemas/fabric/item/report/definition/visualContainer/2.1.0/schema.json",
  "name": "c90e334be0ac5a604b53",
  "position": {
    "x": 1470,
    "y": 350,
    "z": 6500,
    "height": 80,
    "width": 420,
    "tabOrder": 5000
  },
  "visual": {
    "visualType": "slicer",
    "query": {
      "queryState": {
        "Values": {
          "projections": [
            {
              "field": {
                "Column": {
                  "Expression": {
                    "SourceRef": {
                      "Entity": "Index alloc type"
                    }
                  },
                  "Property": "Index"
                }
              },
              "queryRef": "Index alloc type.Index",
              "nativeQueryRef": "Index1",
              "active": true
            }
          ]
        }
      }
    },
    "objects": {
      "general": [
        {
          "properties": {
            "selfFilterEnabled": {
              "expr": {
                "Literal": {
                  "Value": "true"
                }
              }
            }
          }
        }
      ],
      "data": [
        {
          "properties": {
            "mode": {
              "expr": {
                "Literal": {
                  "Value": "'Dropdown'"
                }
              }
            }
          }
        }
      ]
    },
    "visualContainerObjects": {
      "title": [
        {
          "properties": {
            "text": {
              "expr": {
                "Literal": {
                  "Value": "'Index Slicer'"
                }
              }
            }
          }
        }
      ]
    },
    "drillFilterOtherVisuals": true
  },
  "parentGroupName": "dc4977fbc1904070b067",
  "filterConfig": {
    "filters": [
      {
        "name": "dba3cf36db2b634a0284",
        "field": {
          "Measure": {
            "Expression": {
              "SourceRef": {
                "Entity": "_Measures"
              }
            },
            "Property": "VLF Filter - Index physical"
          }
        },
        "type": "Advanced",
        "filter": {
          "Version": 2,
          "From": [
            {
              "Name": "_",
              "Entity": "_Measures",
              "Type": 0
            }
          ],
          "Where": [
            {
              "Condition": {
                "Not": {
                  "Expression": {
                    "Comparison": {
                      "ComparisonKind": 0,
                      "Left": {
                        "Measure": {
                          "Expression": {
                            "SourceRef": {
                              "Source": "_"
                            }
                          },
                          "Property": "VLF Filter - Index physical"
                        }
                      },
                      "Right": {
                        "Literal": {
                          "Value": "null"
                        }
                      }
                    }
                  }
                }
              }
            }
          ]
        },
        "howCreated": "User"
      }
    ]
  }
}