{
  "$schema": "https://developer.microsoft.com/json-schemas/fabric/item/report/definition/bookmark/1.4.0/schema.json",
  "displayName": "Filter panel opened - Database IO",
  "name": "1b4b58969ea71005972b",
  "options": {
    "applyOnlyToTargetVisuals": true,
    "targetVisualNames": [
      "9d76d678d48ccb713ee6",
      "2f35d030ab4806085ada",
      "e75119e922236b8c87a3",
      "e6ca191231ab4931eb1c",
      "f9424b812b0b4247a155",
      "bf3c05b7a0ed9b946071",
      "52a0caed2694e605c686",
      "a07407d54404cc8ae308",
      "33381ed6995260253aed",
      "2857b0cec49ccdbdae35",
      "c0cf216a6cdddff6828e",
      "cfcedd8d5c72d771defb",
      "edec1d7149152cd4390d",
      "666ecf7e70eecfb19d79",
      "5996fb69010110be7fbe",
      "b24babdac006285f519c"
    ],
    "suppressData": true
  },
  "explorationState": {
    "version": "1.3",
    "activeSection": "07bda3c0f5d9d260111f",
    "sections": {
      "07bda3c0f5d9d260111f": {
        "visualContainers": {
          "09431855a927f1ccd435": {
            "filters": {
              "byExpr": [
                {
                  "name": "3716d040bc89c655ead8",
                  "type": "Categorical",
                  "expression": {
                    "Column": {
                      "Expression": {
                        "SourceRef": {
                          "Entity": "Database file"
                        }
                      },
                      "Property": "Type"
                    }
                  },
                  "howCreated": 0
                }
              ]
            },
            "singleVisual": {
              "visualType": "slicer",
              "objects": {
                "merge": {
                  "data": [
                    {
                      "properties": {
                        "mode": {
                          "expr": {
                            "Literal": {
                              "Value": "'Basic'"
                            }
                          }
                        }
                      }
                    }
                  ],
                  "selection": [
                    {
                      "properties": {
                        "strictSingleSelect": {
                          "expr": {
                            "Literal": {
                              "Value": "false"
                            }
                          }
                        }
                      }
                    }
                  ]
                }
              },
              "activeProjections": {
                "Values": [
                  {
                    "Column": {
                      "Expression": {
                        "SourceRef": {
                          "Entity": "Database file"
                        }
                      },
                      "Property": "Type"
                    }
                  }
                ]
              }
            }
          },
          "0aa69e5fdc1a9c2a612f": {
            "filters": {
              "byExpr": [
                {
                  "name": "7a26f676dede6b50ea59",
                  "type": "Categorical",
                  "expression": {
                    "Column": {
                      "Expression": {
                        "SourceRef": {
                          "Entity": "Date"
                        }
                      },
                      "Property": "Date"
                    }
                  },
                  "howCreated": 0
                },
                {
                  "name": "924c76e430832c6446b7",
                  "type": "Advanced",
                  "expression": {
                    "Column": {
                      "Expression": {
                        "SourceRef": {
                          "Entity": "Time"
                        }
                      },
                      "Property": "Hour"
                    }
                  },
                  "howCreated": 0
                },
                {
                  "name": "61c515469e2964d9803d",
                  "type": "Advanced",
                  "expression": {
                    "Column": {
                      "Expression": {
                        "SourceRef": {
                          "Entity": "Time"
                        }
                      },
                      "Property": "Minute"
                    }
                  },
                  "howCreated": 0
                },
                {
                  "name": "78a1680489550db7c1d3",
                  "type": "Advanced",
                  "expression": {
                    "Measure": {
                      "Expression": {
                        "SourceRef": {
                          "Entity": "_Measures"
                        }
                      },
                      "Property": "Number of bytes read MB - Database IO"
                    }
                  },
                  "howCreated": 0
                }
              ]
            },
            "singleVisual": {
              "visualType": "lineChart",
              "objects": {},
              "orderBy": [
                {
                  "Direction": 1,
                  "Expression": {
                    "Column": {
                      "Expression": {
                        "SourceRef": {
                          "Entity": "Date"
                        }
                      },
                      "Property": "Date"
                    }
                  }
                },
                {
                  "Direction": 1,
                  "Expression": {
                    "Column": {
                      "Expression": {
                        "SourceRef": {
                          "Entity": "Time"
                        }
                      },
                      "Property": "Hour"
                    }
                  }
                },
                {
                  "Direction": 1,
                  "Expression": {
                    "Column": {
                      "Expression": {
                        "SourceRef": {
                          "Entity": "Time"
                        }
                      },
                      "Property": "Minute"
                    }
                  }
                }
              ],
              "activeProjections": {
                "Category": [
                  {
                    "Column": {
                      "Expression": {
                        "SourceRef": {
                          "Entity": "Date"
                        }
                      },
                      "Property": "Date"
                    }
                  }
                ]
              }
            }
          },
          "0f48bc7dd6aede5548eb": {
            "singleVisual": {
              "visualType": "actionButton",
              "objects": {}
            }
          },
          "2857b0cec49ccdbdae35": {
            "singleVisual": {
              "visualType": "shape",
              "objects": {}
            }
          },
          "2ce5cd0f825fad7aa287": {
            "filters": {
              "byExpr": [
                {
                  "name": "ce6ac19c0d310dd62173",
                  "type": "Advanced",
                  "expression": {
                    "Measure": {
                      "Expression": {
                        "SourceRef": {
                          "Entity": "_Measures"
                        }
                      },
                      "Property": "Data range - Database IO"
                    }
                  },
                  "howCreated": 0
                }
              ]
            },
            "singleVisual": {
              "visualType": "card",
              "objects": {}
            }
          },
          "2f35d030ab4806085ada": {
            "singleVisual": {
              "visualType": "actionButton",
              "objects": {}
            }
          },
          "33381ed6995260253aed": {
            "singleVisual": {
              "visualType": "actionButton",
              "objects": {}
            }
          },
          "50a97a3d5505d28fe523": {
            "filters": {
              "byExpr": [
                {
                  "name": "8ec9ffb6450500a52656",
                  "type": "Advanced",
                  "expression": {
                    "Measure": {
                      "Expression": {
                        "SourceRef": {
                          "Entity": "_Measures"
                        }
                      },
                      "Property": "Info text"
                    }
                  },
                  "howCreated": 0
                }
              ]
            },
            "singleVisual": {
              "visualType": "card",
              "objects": {}
            }
          },
          "52a0caed2694e605c686": {
            "filters": {
              "byExpr": [
                {
                  "name": "Filter51303ef7785835c0ff0e",
                  "type": "Advanced",
                  "filter": {
                    "Version": 2,
                    "From": [
                      {
                        "Name": "_",
                        "Entity": "_Measures",
                        "Type": 0
                      }
                    ],
                    "Where": [
                      {
                        "Condition": {
                          "Not": {
                            "Expression": {
                              "Comparison": {
                                "ComparisonKind": 0,
                                "Left": {
                                  "Measure": {
                                    "Expression": {
                                      "SourceRef": {
                                        "Source": "_"
                                      }
                                    },
                                    "Property": "Number of bytes read MB - Database IO"
                                  }
                                },
                                "Right": {
                                  "Literal": {
                                    "Value": "null"
                                  }
                                }
                              }
                            }
                          }
                        }
                      }
                    ]
                  },
                  "expression": {
                    "Measure": {
                      "Expression": {
                        "SourceRef": {
                          "Entity": "_Measures"
                        }
                      },
                      "Property": "Number of bytes read MB - Database IO"
                    }
                  },
                  "howCreated": 1
                },
                {
                  "name": "9ffa2e20c2baa045ede6",
                  "type": "Advanced",
                  "expression": {
                    "Column": {
                      "Expression": {
                        "SourceRef": {
                          "Entity": "Date"
                        }
                      },
                      "Property": "Day index"
                    }
                  },
                  "howCreated": 0
                }
              ]
            },
            "singleVisual": {
              "visualType": "slicer",
              "objects": {},
              "activeProjections": {
                "Values": [
                  {
                    "Column": {
                      "Expression": {
                        "SourceRef": {
                          "Entity": "Date"
                        }
                      },
                      "Property": "Day index"
                    }
                  }
                ]
              }
            }
          },
          "554aafda05ed945d52b2": {
            "filters": {
              "byExpr": [
                {
                  "name": "b05741229d2c8b75b3ca",
                  "type": "Categorical",
                  "expression": {
                    "Column": {
                      "Expression": {
                        "SourceRef": {
                          "Entity": "Date"
                        }
                      },
                      "Property": "Date"
                    }
                  },
                  "howCreated": 0
                },
                {
                  "name": "d7c2ad7cd216bed90310",
                  "type": "Advanced",
                  "expression": {
                    "Column": {
                      "Expression": {
                        "SourceRef": {
                          "Entity": "Time"
                        }
                      },
                      "Property": "Hour"
                    }
                  },
                  "howCreated": 0
                },
                {
                  "name": "f601afb03d0cbc47c36c",
                  "type": "Advanced",
                  "expression": {
                    "Column": {
                      "Expression": {
                        "SourceRef": {
                          "Entity": "Time"
                        }
                      },
                      "Property": "Minute"
                    }
                  },
                  "howCreated": 0
                },
                {
                  "name": "e49cd3fc9a25d914cda8",
                  "type": "Advanced",
                  "expression": {
                    "Measure": {
                      "Expression": {
                        "SourceRef": {
                          "Entity": "_Measures"
                        }
                      },
                      "Property": "Number of bytes written MB - Database IO"
                    }
                  },
                  "howCreated": 0
                }
              ]
            },
            "singleVisual": {
              "visualType": "lineChart",
              "objects": {},
              "orderBy": [
                {
                  "Direction": 1,
                  "Expression": {
                    "Column": {
                      "Expression": {
                        "SourceRef": {
                          "Entity": "Date"
                        }
                      },
                      "Property": "Date"
                    }
                  }
                },
                {
                  "Direction": 1,
                  "Expression": {
                    "Column": {
                      "Expression": {
                        "SourceRef": {
                          "Entity": "Time"
                        }
                      },
                      "Property": "Hour"
                    }
                  }
                },
                {
                  "Direction": 1,
                  "Expression": {
                    "Column": {
                      "Expression": {
                        "SourceRef": {
                          "Entity": "Time"
                        }
                      },
                      "Property": "Minute"
                    }
                  }
                }
              ],
              "activeProjections": {
                "Category": [
                  {
                    "Column": {
                      "Expression": {
                        "SourceRef": {
                          "Entity": "Date"
                        }
                      },
                      "Property": "Date"
                    }
                  }
                ]
              }
            }
          },
          "5996fb69010110be7fbe": {
            "filters": {
              "byExpr": [
                {
                  "name": "96372d8573b543c579d4",
                  "type": "Advanced",
                  "expression": {
                    "Measure": {
                      "Expression": {
                        "SourceRef": {
                          "Entity": "_Measures"
                        }
                      },
                      "Property": "Open filter button tooltip - Database IO"
                    }
                  },
                  "howCreated": 0
                }
              ]
            },
            "singleVisual": {
              "visualType": "card",
              "objects": {}
            }
          },
          "6203c6be1c91b8f7471d": {
            "filters": {
              "byExpr": [
                {
                  "name": "431a8bd02622105d07c4",
                  "type": "Categorical",
                  "expression": {
                    "Column": {
                      "Expression": {
                        "SourceRef": {
                          "Entity": "Date"
                        }
                      },
                      "Property": "Date"
                    }
                  },
                  "howCreated": 0
                },
                {
                  "name": "b8bca9bbd6a7554b700a",
                  "type": "Advanced",
                  "expression": {
                    "Column": {
                      "Expression": {
                        "SourceRef": {
                          "Entity": "Time"
                        }
                      },
                      "Property": "Hour"
                    }
                  },
                  "howCreated": 0
                },
                {
                  "name": "c97ee6ac92796284a0ee",
                  "type": "Advanced",
                  "expression": {
                    "Column": {
                      "Expression": {
                        "SourceRef": {
                          "Entity": "Time"
                        }
                      },
                      "Property": "Minute"
                    }
                  },
                  "howCreated": 0
                },
                {
                  "name": "d7d77fa1857e09d9e79a",
                  "type": "Advanced",
                  "expression": {
                    "Measure": {
                      "Expression": {
                        "SourceRef": {
                          "Entity": "_Measures"
                        }
                      },
                      "Property": "Max write latency mS - Database IO"
                    }
                  },
                  "howCreated": 0
                },
                {
                  "name": "d42cca2a376e98d545a0",
                  "type": "Advanced",
                  "expression": {
                    "Measure": {
                      "Expression": {
                        "SourceRef": {
                          "Entity": "_Measures"
                        }
                      },
                      "Property": "Avg. write latency mS - Database IO"
                    }
                  },
                  "howCreated": 0
                },
                {
                  "name": "caf9bf1574c1384c180e",
                  "type": "Advanced",
                  "expression": {
                    "Measure": {
                      "Expression": {
                        "SourceRef": {
                          "Entity": "_Measures"
                        }
                      },
                      "Property": "Min write latency mS - Database IO"
                    }
                  },
                  "howCreated": 0
                }
              ]
            },
            "singleVisual": {
              "visualType": "lineChart",
              "objects": {},
              "orderBy": [
                {
                  "Direction": 1,
                  "Expression": {
                    "Column": {
                      "Expression": {
                        "SourceRef": {
                          "Entity": "Date"
                        }
                      },
                      "Property": "Date"
                    }
                  }
                },
                {
                  "Direction": 1,
                  "Expression": {
                    "Column": {
                      "Expression": {
                        "SourceRef": {
                          "Entity": "Time"
                        }
                      },
                      "Property": "Hour"
                    }
                  }
                },
                {
                  "Direction": 1,
                  "Expression": {
                    "Column": {
                      "Expression": {
                        "SourceRef": {
                          "Entity": "Time"
                        }
                      },
                      "Property": "Minute"
                    }
                  }
                }
              ],
              "activeProjections": {
                "Category": [
                  {
                    "Column": {
                      "Expression": {
                        "SourceRef": {
                          "Entity": "Date"
                        }
                      },
                      "Property": "Date"
                    }
                  }
                ]
              }
            }
          },
          "70698622a1238cd811c4": {
            "filters": {
              "byExpr": [
                {
                  "name": "d1444bfd57bc9a7beb5e",
                  "type": "Categorical",
                  "expression": {
                    "Column": {
                      "Expression": {
                        "SourceRef": {
                          "Entity": "Database file"
                        }
                      },
                      "Property": "Database"
                    }
                  },
                  "howCreated": 0
                },
                {
                  "name": "58337e19b1ba2a40a0e5",
                  "type": "Categorical",
                  "expression": {
                    "Column": {
                      "Expression": {
                        "SourceRef": {
                          "Entity": "Database file"
                        }
                      },
                      "Property": "Logical file"
                    }
                  },
                  "howCreated": 0
                },
                {
                  "name": "9e170e9b201011e19a30",
                  "type": "Categorical",
                  "expression": {
                    "Column": {
                      "Expression": {
                        "SourceRef": {
                          "Entity": "Database file"
                        }
                      },
                      "Property": "Type"
                    }
                  },
                  "howCreated": 0
                },
                {
                  "name": "aea46f26c14e151260ec",
                  "type": "Advanced",
                  "expression": {
                    "Measure": {
                      "Expression": {
                        "SourceRef": {
                          "Entity": "_Measures"
                        }
                      },
                      "Property": "Latest day number of bytes read MB - Database IO"
                    }
                  },
                  "howCreated": 0
                },
                {
                  "name": "12834996201108e841da",
                  "type": "Advanced",
                  "expression": {
                    "Measure": {
                      "Expression": {
                        "SourceRef": {
                          "Entity": "_Measures"
                        }
                      },
                      "Property": "Number of bytes read ratio of total - Database IO"
                    }
                  },
                  "howCreated": 0
                },
                {
                  "name": "b754d709de3b2645be0e",
                  "type": "Advanced",
                  "expression": {
                    "Measure": {
                      "Expression": {
                        "SourceRef": {
                          "Entity": "_Measures"
                        }
                      },
                      "Property": "Past day number of bytes read MB - Database IO"
                    }
                  },
                  "howCreated": 0
                },
                {
                  "name": "6f428b5d5a594a8067ed",
                  "type": "Advanced",
                  "expression": {
                    "Measure": {
                      "Expression": {
                        "SourceRef": {
                          "Entity": "_Measures"
                        }
                      },
                      "Property": "Number of bytes read ratio since past - Database IO"
                    }
                  },
                  "howCreated": 0
                }
              ]
            },
            "singleVisual": {
              "visualType": "pivotTable",
              "objects": {},
              "orderBy": [
                {
                  "Direction": 2,
                  "Expression": {
                    "Measure": {
                      "Expression": {
                        "SourceRef": {
                          "Entity": "_Measures"
                        }
                      },
                      "Property": "Latest day number of bytes read MB - Database IO"
                    }
                  }
                }
              ],
              "activeProjections": {
                "Rows": [
                  {
                    "Column": {
                      "Expression": {
                        "SourceRef": {
                          "Entity": "Database file"
                        }
                      },
                      "Property": "Database"
                    }
                  }
                ]
              },
              "expansionStates": [
                {
                  "roles": [
                    "Rows"
                  ],
                  "levels": [
                    {
                      "queryRefs": [
                        "Database file.Database name"
                      ],
                      "isCollapsed": true,
                      "identityKeys": [
                        {
                          "Column": {
                            "Expression": {
                              "SourceRef": {
                                "Entity": "Database file"
                              }
                            },
                            "Property": "Database"
                          }
                        }
                      ],
                      "isPinned": true
                    },
                    {
                      "queryRefs": [
                        "Database file.Type"
                      ],
                      "isCollapsed": true,
                      "identityKeys": [
                        {
                          "Column": {
                            "Expression": {
                              "SourceRef": {
                                "Entity": "Database file"
                              }
                            },
                            "Property": "Type"
                          }
                        }
                      ],
                      "isPinned": true
                    },
                    {
                      "queryRefs": [
                        "Database file.Logical name"
                      ],
                      "isCollapsed": true,
                      "isPinned": true
                    }
                  ],
                  "root": {
                    "identityValues": null
                  }
                }
              ]
            }
          },
          "76836918753470356081": {
            "filters": {
              "byExpr": [
                {
                  "name": "afe7119dea69b1793641",
                  "type": "Categorical",
                  "expression": {
                    "Column": {
                      "Expression": {
                        "SourceRef": {
                          "Entity": "Date"
                        }
                      },
                      "Property": "Date"
                    }
                  },
                  "howCreated": 0
                },
                {
                  "name": "97ddbd538b89d360856c",
                  "type": "Advanced",
                  "expression": {
                    "Column": {
                      "Expression": {
                        "SourceRef": {
                          "Entity": "Time"
                        }
                      },
                      "Property": "Hour"
                    }
                  },
                  "howCreated": 0
                },
                {
                  "name": "584b8723e05207cd5bca",
                  "type": "Advanced",
                  "expression": {
                    "Column": {
                      "Expression": {
                        "SourceRef": {
                          "Entity": "Time"
                        }
                      },
                      "Property": "Minute"
                    }
                  },
                  "howCreated": 0
                },
                {
                  "name": "f57d3e93040702a85140",
                  "type": "Advanced",
                  "expression": {
                    "Measure": {
                      "Expression": {
                        "SourceRef": {
                          "Entity": "_Measures"
                        }
                      },
                      "Property": "Max read latency mS - Database IO"
                    }
                  },
                  "howCreated": 0
                },
                {
                  "name": "561e3da5728d7a22e224",
                  "type": "Advanced",
                  "expression": {
                    "Measure": {
                      "Expression": {
                        "SourceRef": {
                          "Entity": "_Measures"
                        }
                      },
                      "Property": "Avg. read latency mS - Database IO"
                    }
                  },
                  "howCreated": 0
                },
                {
                  "name": "6b5f441c852430a085d3",
                  "type": "Advanced",
                  "expression": {
                    "Measure": {
                      "Expression": {
                        "SourceRef": {
                          "Entity": "_Measures"
                        }
                      },
                      "Property": "Min read latency mS - Database IO"
                    }
                  },
                  "howCreated": 0
                }
              ]
            },
            "singleVisual": {
              "visualType": "lineChart",
              "objects": {},
              "orderBy": [
                {
                  "Direction": 1,
                  "Expression": {
                    "Column": {
                      "Expression": {
                        "SourceRef": {
                          "Entity": "Date"
                        }
                      },
                      "Property": "Date"
                    }
                  }
                },
                {
                  "Direction": 1,
                  "Expression": {
                    "Column": {
                      "Expression": {
                        "SourceRef": {
                          "Entity": "Time"
                        }
                      },
                      "Property": "Hour"
                    }
                  }
                },
                {
                  "Direction": 1,
                  "Expression": {
                    "Column": {
                      "Expression": {
                        "SourceRef": {
                          "Entity": "Time"
                        }
                      },
                      "Property": "Minute"
                    }
                  }
                }
              ],
              "activeProjections": {
                "Category": [
                  {
                    "Column": {
                      "Expression": {
                        "SourceRef": {
                          "Entity": "Date"
                        }
                      },
                      "Property": "Date"
                    }
                  }
                ]
              }
            }
          },
          "9ff0a1eccb02f0567419": {
            "filters": {
              "byExpr": [
                {
                  "name": "4f8464100d25d9b19927",
                  "type": "Categorical",
                  "expression": {
                    "Column": {
                      "Expression": {
                        "SourceRef": {
                          "Entity": "Database file"
                        }
                      },
                      "Property": "Database"
                    }
                  },
                  "howCreated": 0
                },
                {
                  "name": "8240b5c4dcad5b175272",
                  "type": "Categorical",
                  "expression": {
                    "Column": {
                      "Expression": {
                        "SourceRef": {
                          "Entity": "Database file"
                        }
                      },
                      "Property": "Logical file"
                    }
                  },
                  "howCreated": 0
                },
                {
                  "name": "4e82db70c80ad9e18980",
                  "type": "Categorical",
                  "expression": {
                    "Column": {
                      "Expression": {
                        "SourceRef": {
                          "Entity": "Database file"
                        }
                      },
                      "Property": "Type"
                    }
                  },
                  "howCreated": 0
                },
                {
                  "name": "a09781fcee98ed46a354",
                  "type": "Advanced",
                  "expression": {
                    "Measure": {
                      "Expression": {
                        "SourceRef": {
                          "Entity": "_Measures"
                        }
                      },
                      "Property": "Latest day number of bytes written MB - Database IO"
                    }
                  },
                  "howCreated": 0
                },
                {
                  "name": "f57a1dcadd438cc71b83",
                  "type": "Advanced",
                  "expression": {
                    "Measure": {
                      "Expression": {
                        "SourceRef": {
                          "Entity": "_Measures"
                        }
                      },
                      "Property": "Number of bytes written ratio of total - Database IO"
                    }
                  },
                  "howCreated": 0
                },
                {
                  "name": "e07fa62fcd8d40d97412",
                  "type": "Advanced",
                  "expression": {
                    "Measure": {
                      "Expression": {
                        "SourceRef": {
                          "Entity": "_Measures"
                        }
                      },
                      "Property": "Past day number of bytes written MB - Database IO"
                    }
                  },
                  "howCreated": 0
                },
                {
                  "name": "9e67783006b21ae64e44",
                  "type": "Advanced",
                  "expression": {
                    "Measure": {
                      "Expression": {
                        "SourceRef": {
                          "Entity": "_Measures"
                        }
                      },
                      "Property": "Number of bytes written ratio since past - Database IO"
                    }
                  },
                  "howCreated": 0
                }
              ]
            },
            "singleVisual": {
              "visualType": "pivotTable",
              "objects": {},
              "orderBy": [
                {
                  "Direction": 2,
                  "Expression": {
                    "Measure": {
                      "Expression": {
                        "SourceRef": {
                          "Entity": "_Measures"
                        }
                      },
                      "Property": "Latest day number of bytes written MB - Database IO"
                    }
                  }
                }
              ],
              "activeProjections": {
                "Rows": [
                  {
                    "Column": {
                      "Expression": {
                        "SourceRef": {
                          "Entity": "Database file"
                        }
                      },
                      "Property": "Database"
                    }
                  }
                ]
              }
            }
          },
          "a07407d54404cc8ae308": {
            "filters": {
              "byExpr": [
                {
                  "name": "Filter51303ef7785835c0ff0e",
                  "type": "Advanced",
                  "filter": {
                    "Version": 2,
                    "From": [
                      {
                        "Name": "_",
                        "Entity": "_Measures",
                        "Type": 0
                      }
                    ],
                    "Where": [
                      {
                        "Condition": {
                          "Not": {
                            "Expression": {
                              "Comparison": {
                                "ComparisonKind": 0,
                                "Left": {
                                  "Measure": {
                                    "Expression": {
                                      "SourceRef": {
                                        "Source": "_"
                                      }
                                    },
                                    "Property": "Number of bytes read MB - Database IO"
                                  }
                                },
                                "Right": {
                                  "Literal": {
                                    "Value": "null"
                                  }
                                }
                              }
                            }
                          }
                        }
                      }
                    ]
                  },
                  "expression": {
                    "Measure": {
                      "Expression": {
                        "SourceRef": {
                          "Entity": "_Measures"
                        }
                      },
                      "Property": "Number of bytes read MB - Database IO"
                    }
                  },
                  "howCreated": 1
                },
                {
                  "name": "c32f0c0d4203ee7be768",
                  "type": "Advanced",
                  "expression": {
                    "Column": {
                      "Expression": {
                        "SourceRef": {
                          "Entity": "Time"
                        }
                      },
                      "Property": "Hour"
                    }
                  },
                  "howCreated": 0
                }
              ]
            },
            "singleVisual": {
              "visualType": "slicer",
              "objects": {},
              "activeProjections": {
                "Values": [
                  {
                    "Column": {
                      "Expression": {
                        "SourceRef": {
                          "Entity": "Time"
                        }
                      },
                      "Property": "Hour"
                    }
                  }
                ]
              }
            }
          },
          "b24babdac006285f519c": {
            "singleVisual": {
              "visualType": "actionButton",
              "objects": {}
            }
          },
          "b5909c6d6eba2e713931": {
            "filters": {
              "byExpr": [
                {
                  "name": "a96d5f5cad02e5a4740b",
                  "type": "Advanced",
                  "expression": {
                    "Column": {
                      "Expression": {
                        "SourceRef": {
                          "Entity": "Tally1"
                        }
                      },
                      "Property": "Value"
                    }
                  },
                  "howCreated": 0
                }
              ]
            },
            "singleVisual": {
              "visualType": "slicer",
              "objects": {
                "merge": {
                  "general": [
                    {
                      "properties": {
                        "filter": {
                          "filter": {
                            "Version": 2,
                            "From": [
                              {
                                "Name": "t",
                                "Entity": "Tally1",
                                "Type": 0
                              }
                            ],
                            "Where": [
                              {
                                "Condition": {
                                  "In": {
                                    "Expressions": [
                                      {
                                        "Column": {
                                          "Expression": {
                                            "SourceRef": {
                                              "Source": "t"
                                            }
                                          },
                                          "Property": "Value"
                                        }
                                      }
                                    ],
                                    "Values": [
                                      [
                                        {
                                          "Literal": {
                                            "Value": "30L"
                                          }
                                        }
                                      ]
                                    ]
                                  }
                                }
                              }
                            ]
                          }
                        }
                      }
                    }
                  ],
                  "data": [
                    {
                      "properties": {
                        "mode": {
                          "expr": {
                            "Literal": {
                              "Value": "'Dropdown'"
                            }
                          }
                        }
                      }
                    }
                  ],
                  "selection": [
                    {
                      "properties": {
                        "strictSingleSelect": {
                          "expr": {
                            "Literal": {
                              "Value": "true"
                            }
                          }
                        }
                      }
                    }
                  ]
                }
              },
              "activeProjections": {
                "Values": [
                  {
                    "Column": {
                      "Expression": {
                        "SourceRef": {
                          "Entity": "Tally1"
                        }
                      },
                      "Property": "Value"
                    }
                  }
                ]
              }
            }
          },
          "bf3c05b7a0ed9b946071": {
            "filters": {
              "byExpr": [
                {
                  "name": "Filter51303ef7785835c0ff0e",
                  "type": "Advanced",
                  "filter": {
                    "Version": 2,
                    "From": [
                      {
                        "Name": "_",
                        "Entity": "_Measures",
                        "Type": 0
                      }
                    ],
                    "Where": [
                      {
                        "Condition": {
                          "Not": {
                            "Expression": {
                              "Comparison": {
                                "ComparisonKind": 0,
                                "Left": {
                                  "Measure": {
                                    "Expression": {
                                      "SourceRef": {
                                        "Source": "_"
                                      }
                                    },
                                    "Property": "Number of bytes read MB - Database IO"
                                  }
                                },
                                "Right": {
                                  "Literal": {
                                    "Value": "null"
                                  }
                                }
                              }
                            }
                          }
                        }
                      }
                    ]
                  },
                  "expression": {
                    "Measure": {
                      "Expression": {
                        "SourceRef": {
                          "Entity": "_Measures"
                        }
                      },
                      "Property": "Number of bytes read MB - Database IO"
                    }
                  },
                  "howCreated": 1
                },
                {
                  "name": "7404bf464061aad1d047",
                  "type": "Advanced",
                  "expression": {
                    "Column": {
                      "Expression": {
                        "SourceRef": {
                          "Entity": "Date"
                        }
                      },
                      "Property": "Day"
                    }
                  },
                  "howCreated": 0
                }
              ]
            },
            "singleVisual": {
              "visualType": "slicer",
              "objects": {},
              "activeProjections": {
                "Values": [
                  {
                    "Column": {
                      "Expression": {
                        "SourceRef": {
                          "Entity": "Date"
                        }
                      },
                      "Property": "Day"
                    }
                  }
                ]
              }
            }
          },
          "c0cf216a6cdddff6828e": {
            "filters": {
              "byExpr": [
                {
                  "name": "cba9bda30c090564a50c",
                  "type": "Advanced",
                  "expression": {
                    "Measure": {
                      "Expression": {
                        "SourceRef": {
                          "Entity": "_Measures"
                        }
                      },
                      "Property": "Show filters Headers - Database IO"
                    }
                  },
                  "howCreated": 0
                },
                {
                  "name": "552fe6667105c7a3bcb6",
                  "type": "Advanced",
                  "expression": {
                    "Measure": {
                      "Expression": {
                        "SourceRef": {
                          "Entity": "_Measures"
                        }
                      },
                      "Property": "Show filters - Database IO"
                    }
                  },
                  "howCreated": 0
                }
              ]
            },
            "singleVisual": {
              "visualType": "tableEx",
              "objects": {}
            }
          },
          "cda7dbd6fbafc1b75fd0": {
            "singleVisual": {
              "visualType": "actionButton",
              "objects": {}
            }
          },
          "cfcedd8d5c72d771defb": {
            "singleVisual": {
              "visualType": "shape",
              "objects": {}
            }
          },
          "d3103dc8e8367f3d8d98": {
            "filters": {
              "byExpr": [
                {
                  "name": "b7c553fd57bcd8690d85",
                  "type": "Advanced",
                  "expression": {
                    "Measure": {
                      "Expression": {
                        "SourceRef": {
                          "Entity": "_Measures"
                        }
                      },
                      "Property": "Info last refresh"
                    }
                  },
                  "howCreated": 0
                }
              ]
            },
            "singleVisual": {
              "visualType": "card",
              "objects": {}
            }
          },
          "e6ca191231ab4931eb1c": {
            "filters": {
              "byExpr": [
                {
                  "name": "Filter17861b12ce055d6b77e2",
                  "type": "Advanced",
                  "filter": {
                    "Version": 2,
                    "From": [
                      {
                        "Name": "_",
                        "Entity": "_Measures",
                        "Type": 0
                      }
                    ],
                    "Where": [
                      {
                        "Condition": {
                          "Not": {
                            "Expression": {
                              "Comparison": {
                                "ComparisonKind": 0,
                                "Left": {
                                  "Measure": {
                                    "Expression": {
                                      "SourceRef": {
                                        "Source": "_"
                                      }
                                    },
                                    "Property": "Number of bytes read MB - Database IO"
                                  }
                                },
                                "Right": {
                                  "Literal": {
                                    "Value": "null"
                                  }
                                }
                              }
                            }
                          }
                        }
                      }
                    ]
                  },
                  "expression": {
                    "Measure": {
                      "Expression": {
                        "SourceRef": {
                          "Entity": "_Measures"
                        }
                      },
                      "Property": "Number of bytes read MB - Database IO"
                    }
                  },
                  "howCreated": 1
                },
                {
                  "name": "d4d3d1068e2019651a02",
                  "type": "Advanced",
                  "expression": {
                    "Column": {
                      "Expression": {
                        "SourceRef": {
                          "Entity": "Date"
                        }
                      },
                      "Property": "Year"
                    }
                  },
                  "howCreated": 0
                }
              ]
            },
            "singleVisual": {
              "visualType": "slicer",
              "objects": {},
              "activeProjections": {
                "Values": [
                  {
                    "Column": {
                      "Expression": {
                        "SourceRef": {
                          "Entity": "Date"
                        }
                      },
                      "Property": "Year"
                    }
                  }
                ]
              }
            }
          },
          "e75119e922236b8c87a3": {
            "filters": {
              "byExpr": [
                {
                  "name": "Filter122fd08d2ca4b769df75",
                  "type": "Advanced",
                  "filter": {
                    "Version": 2,
                    "From": [
                      {
                        "Name": "_",
                        "Entity": "_Measures",
                        "Type": 0
                      }
                    ],
                    "Where": [
                      {
                        "Condition": {
                          "Not": {
                            "Expression": {
                              "Comparison": {
                                "ComparisonKind": 0,
                                "Left": {
                                  "Measure": {
                                    "Expression": {
                                      "SourceRef": {
                                        "Source": "_"
                                      }
                                    },
                                    "Property": "Number of bytes read MB - Database IO"
                                  }
                                },
                                "Right": {
                                  "Literal": {
                                    "Value": "null"
                                  }
                                }
                              }
                            }
                          }
                        }
                      }
                    ]
                  },
                  "expression": {
                    "Measure": {
                      "Expression": {
                        "SourceRef": {
                          "Entity": "_Measures"
                        }
                      },
                      "Property": "Number of bytes read MB - Database IO"
                    }
                  },
                  "howCreated": 1
                },
                {
                  "name": "28ce877ac234e64dc10c",
                  "type": "Categorical",
                  "expression": {
                    "Column": {
                      "Expression": {
                        "SourceRef": {
                          "Entity": "Database file"
                        }
                      },
                      "Property": "Database"
                    }
                  },
                  "howCreated": 0
                }
              ]
            },
            "singleVisual": {
              "visualType": "slicer",
              "objects": {},
              "activeProjections": {
                "Values": [
                  {
                    "Column": {
                      "Expression": {
                        "SourceRef": {
                          "Entity": "Database file"
                        }
                      },
                      "Property": "Database"
                    }
                  }
                ]
              }
            }
          },
          "edec1d7149152cd4390d": {
            "singleVisual": {
              "visualType": "shape",
              "objects": {}
            }
          },
          "f9424b812b0b4247a155": {
            "filters": {
              "byExpr": [
                {
                  "name": "Filter51303ef7785835c0ff0e",
                  "type": "Advanced",
                  "filter": {
                    "Version": 2,
                    "From": [
                      {
                        "Name": "_",
                        "Entity": "_Measures",
                        "Type": 0
                      }
                    ],
                    "Where": [
                      {
                        "Condition": {
                          "Not": {
                            "Expression": {
                              "Comparison": {
                                "ComparisonKind": 0,
                                "Left": {
                                  "Measure": {
                                    "Expression": {
                                      "SourceRef": {
                                        "Source": "_"
                                      }
                                    },
                                    "Property": "Number of bytes read MB - Database IO"
                                  }
                                },
                                "Right": {
                                  "Literal": {
                                    "Value": "null"
                                  }
                                }
                              }
                            }
                          }
                        }
                      }
                    ]
                  },
                  "expression": {
                    "Measure": {
                      "Expression": {
                        "SourceRef": {
                          "Entity": "_Measures"
                        }
                      },
                      "Property": "Number of bytes read MB - Database IO"
                    }
                  },
                  "howCreated": 1
                },
                {
                  "name": "2a97395f28bd8a0b34e0",
                  "type": "Categorical",
                  "expression": {
                    "Column": {
                      "Expression": {
                        "SourceRef": {
                          "Entity": "Date"
                        }
                      },
                      "Property": "Month"
                    }
                  },
                  "howCreated": 0
                }
              ]
            },
            "singleVisual": {
              "visualType": "slicer",
              "objects": {},
              "activeProjections": {
                "Values": [
                  {
                    "Column": {
                      "Expression": {
                        "SourceRef": {
                          "Entity": "Date"
                        }
                      },
                      "Property": "Month"
                    }
                  }
                ]
              }
            }
          }
        },
        "visualContainerGroups": {
          "666ecf7e70eecfb19d79": {
            "isHidden": true
          },
          "9d76d678d48ccb713ee6": {
            "isHidden": false
          }
        }
      }
    },
    "objects": {}
  }
}