{
  "$schema": "https://developer.microsoft.com/json-schemas/fabric/item/report/definition/bookmark/1.4.0/schema.json",
  "displayName": "Filter panel opened - Instance status",
  "name": "51305957e08e43eb0b2e",
  "options": {
    "applyOnlyToTargetVisuals": true,
    "targetVisualNames": [
      "046cbda50e6c2907e052",
      "037dbe7e00733d80c1b2",
      "845753a082e40207812a",
      "2bc225e1d00ae373b994",
      "df0cf490b37c9549747c",
      "a71ac7dec0de948e7d38",
      "324b4d54552e3e1a6520",
      "8bd44ad8b537661a0384",
      "e28d7322462dd06240eb",
      "86e8f2d1195b046408c9",
      "8a86d81f68eb8828c787",
      "b2f3dc15270ca2651135",
      "69662287741d0dd50bb0",
      "1a8a2deee0069a30e2b6"
    ],
    "suppressData": true
  },
  "explorationState": {
    "version": "1.3",
    "activeSection": "7aebbb310802b0d2b49b",
    "sections": {
      "7aebbb310802b0d2b49b": {
        "filters": {
          "byName": {
            "76cab435db4b9ad8edc5": {
              "name": "76cab435db4b9ad8edc5",
              "type": "Categorical",
              "filter": {
                "Version": 2,
                "From": [
                  {
                    "Name": "d",
                    "Entity": "Documentation - report pages",
                    "Type": 0
                  }
                ],
                "Where": [
                  {
                    "Condition": {
                      "In": {
                        "Expressions": [
                          {
                            "Column": {
                              "Expression": {
                                "SourceRef": {
                                  "Source": "d"
                                }
                              },
                              "Property": "Page"
                            }
                          }
                        ],
                        "Values": [
                          [
                            {
                              "Literal": {
                                "Value": "'Instance status'"
                              }
                            }
                          ]
                        ]
                      }
                    }
                  }
                ]
              },
              "expression": {
                "Column": {
                  "Expression": {
                    "SourceRef": {
                      "Entity": "Documentation - report pages"
                    }
                  },
                  "Property": "Page"
                }
              },
              "howCreated": 1
            }
          }
        },
        "visualContainers": {
          "07ae7d9a40624a390d71": {
            "filters": {
              "byExpr": [
                {
                  "name": "c8c85bbbe8ccb31bcbc1",
                  "type": "Categorical",
                  "expression": {
                    "Column": {
                      "Expression": {
                        "SourceRef": {
                          "Entity": "Error logs"
                        }
                      },
                      "Property": "Timestamp"
                    }
                  },
                  "howCreated": 0
                },
                {
                  "name": "78b6fbd08a10863a5e39",
                  "type": "Categorical",
                  "expression": {
                    "Column": {
                      "Expression": {
                        "SourceRef": {
                          "Entity": "Error logs"
                        }
                      },
                      "Property": "Process info."
                    }
                  },
                  "howCreated": 0
                },
                {
                  "name": "e34e2ddb8a1724430a45",
                  "type": "Categorical",
                  "expression": {
                    "Column": {
                      "Expression": {
                        "SourceRef": {
                          "Entity": "Error logs"
                        }
                      },
                      "Property": "Text"
                    }
                  },
                  "howCreated": 0
                },
                {
                  "name": "38da5f302c5a42a07440",
                  "type": "Advanced",
                  "expression": {
                    "Column": {
                      "Expression": {
                        "SourceRef": {
                          "Entity": "Error logs"
                        }
                      },
                      "Property": "SetId"
                    }
                  },
                  "howCreated": 0
                },
                {
                  "name": "101a43509bcd0400b370",
                  "type": "Advanced",
                  "expression": {
                    "Column": {
                      "Expression": {
                        "SourceRef": {
                          "Entity": "Error logs"
                        }
                      },
                      "Property": "Id"
                    }
                  },
                  "howCreated": 0
                },
                {
                  "name": "2f4a9b234837ecd487b8",
                  "type": "Advanced",
                  "expression": {
                    "Column": {
                      "Expression": {
                        "SourceRef": {
                          "Entity": "Error logs"
                        }
                      },
                      "Property": "Severity"
                    }
                  },
                  "howCreated": 0
                }
              ]
            },
            "singleVisual": {
              "visualType": "tableEx",
              "objects": {},
              "orderBy": [
                {
                  "Direction": 2,
                  "Expression": {
                    "Column": {
                      "Expression": {
                        "SourceRef": {
                          "Entity": "Error logs"
                        }
                      },
                      "Property": "Id"
                    }
                  }
                }
              ]
            }
          },
          "30d8dac59ebbe4e42d24": {
            "singleVisual": {
              "visualType": "textbox",
              "objects": {}
            }
          },
          "5cfab693c11a2ad090ea": {
            "filters": {
              "byExpr": [
                {
                  "name": "429dfbc7da4d9903dc03",
                  "type": "Advanced",
                  "expression": {
                    "Measure": {
                      "Expression": {
                        "SourceRef": {
                          "Entity": "_Measures"
                        }
                      },
                      "Property": "Info text"
                    }
                  },
                  "howCreated": 0
                }
              ]
            },
            "singleVisual": {
              "visualType": "card",
              "objects": {}
            }
          },
          "60c1036538e6b090395a": {
            "filters": {
              "byExpr": [
                {
                  "name": "1eb1b26fc1a540e88680",
                  "type": "Advanced",
                  "expression": {
                    "Measure": {
                      "Expression": {
                        "SourceRef": {
                          "Entity": "_Measures"
                        }
                      },
                      "Property": "Info last refresh"
                    }
                  },
                  "howCreated": 0
                }
              ]
            },
            "singleVisual": {
              "visualType": "card",
              "objects": {}
            }
          },
          "64da530ea29910dd787e": {
            "singleVisual": {
              "visualType": "actionButton",
              "objects": {}
            }
          },
          "ac13d7ce2a8532199a88": {
            "filters": {
              "byExpr": [
                {
                  "name": "4633e130ea55e7859dee",
                  "type": "Categorical",
                  "expression": {
                    "Column": {
                      "Expression": {
                        "SourceRef": {
                          "Entity": "Instance dump files"
                        }
                      },
                      "Property": "Sequence"
                    }
                  },
                  "howCreated": 0
                },
                {
                  "name": "1546e0756670a56b5742",
                  "type": "Advanced",
                  "expression": {
                    "Measure": {
                      "Expression": {
                        "SourceRef": {
                          "Entity": "_Measures"
                        }
                      },
                      "Property": "Size in bytes - Instance status"
                    }
                  },
                  "howCreated": 0
                },
                {
                  "name": "1f97fc8de1b9be3d566b",
                  "type": "Categorical",
                  "expression": {
                    "Column": {
                      "Expression": {
                        "SourceRef": {
                          "Entity": "Instance dump files"
                        }
                      },
                      "Property": "Created"
                    }
                  },
                  "howCreated": 0
                },
                {
                  "name": "346f80d458a6c2d7176d",
                  "type": "Categorical",
                  "expression": {
                    "Column": {
                      "Expression": {
                        "SourceRef": {
                          "Entity": "Instance dump files"
                        }
                      },
                      "Property": "Filename"
                    }
                  },
                  "howCreated": 0
                }
              ]
            },
            "singleVisual": {
              "visualType": "tableEx",
              "objects": {},
              "orderBy": [
                {
                  "Direction": 2,
                  "Expression": {
                    "Column": {
                      "Expression": {
                        "SourceRef": {
                          "Entity": "Instance dump files"
                        }
                      },
                      "Property": "Created"
                    }
                  }
                }
              ]
            }
          },
          "aeed453309ccbe41ec7d": {
            "singleVisual": {
              "visualType": "actionButton",
              "objects": {}
            }
          },
          "daa394f72ba5888740ee": {
            "filters": {
              "byExpr": [
                {
                  "name": "c4c9b978d972e2ae955e",
                  "type": "Advanced",
                  "expression": {
                    "Measure": {
                      "Expression": {
                        "SourceRef": {
                          "Entity": "_Measures"
                        }
                      },
                      "Property": "Data range - Instance status"
                    }
                  },
                  "howCreated": 0
                }
              ]
            },
            "singleVisual": {
              "visualType": "card",
              "objects": {}
            }
          },
          "f86dc6aa6a6a0029ab1d": {
            "singleVisual": {
              "visualType": "actionButton",
              "objects": {}
            }
          },
          "fdd2e1c7070dd0b8902c": {
            "filters": {
              "byExpr": [
                {
                  "name": "8ba73cb4d22c4151134c",
                  "type": "Categorical",
                  "expression": {
                    "Column": {
                      "Expression": {
                        "SourceRef": {
                          "Entity": "Instance suspect pages"
                        }
                      },
                      "Property": "Database"
                    }
                  },
                  "howCreated": 0
                },
                {
                  "name": "4d6bc2962355378d2162",
                  "type": "Advanced",
                  "expression": {
                    "Column": {
                      "Expression": {
                        "SourceRef": {
                          "Entity": "Instance suspect pages"
                        }
                      },
                      "Property": "FileId"
                    }
                  },
                  "howCreated": 0
                },
                {
                  "name": "19cb1f545040c98187b8",
                  "type": "Advanced",
                  "expression": {
                    "Column": {
                      "Expression": {
                        "SourceRef": {
                          "Entity": "Instance suspect pages"
                        }
                      },
                      "Property": "PageId"
                    }
                  },
                  "howCreated": 0
                },
                {
                  "name": "859f6c525691d2d901b0",
                  "type": "Advanced",
                  "expression": {
                    "Column": {
                      "Expression": {
                        "SourceRef": {
                          "Entity": "Instance suspect pages"
                        }
                      },
                      "Property": "ErrorCount"
                    }
                  },
                  "howCreated": 0
                },
                {
                  "name": "7dc28f346e1e706da03c",
                  "type": "Categorical",
                  "expression": {
                    "Column": {
                      "Expression": {
                        "SourceRef": {
                          "Entity": "Instance suspect pages"
                        }
                      },
                      "Property": "EventType"
                    }
                  },
                  "howCreated": 0
                },
                {
                  "name": "b112a075b00006378045",
                  "type": "Categorical",
                  "expression": {
                    "Column": {
                      "Expression": {
                        "SourceRef": {
                          "Entity": "Instance suspect pages"
                        }
                      },
                      "Property": "Updated"
                    }
                  },
                  "howCreated": 0
                }
              ]
            },
            "singleVisual": {
              "visualType": "tableEx",
              "objects": {},
              "orderBy": [
                {
                  "Direction": 2,
                  "Expression": {
                    "Column": {
                      "Expression": {
                        "SourceRef": {
                          "Entity": "Instance suspect pages"
                        }
                      },
                      "Property": "Updated"
                    }
                  }
                }
              ]
            }
          },
          "845753a082e40207812a": {
            "singleVisual": {
              "visualType": "shape",
              "objects": {}
            }
          },
          "2bc225e1d00ae373b994": {
            "singleVisual": {
              "visualType": "actionButton",
              "objects": {}
            }
          },
          "df0cf490b37c9549747c": {
            "singleVisual": {
              "visualType": "actionButton",
              "objects": {}
            }
          },
          "a71ac7dec0de948e7d38": {
            "filters": {
              "byExpr": [
                {
                  "name": "a2649b89becd4ac40509",
                  "type": "Advanced",
                  "expression": {
                    "Column": {
                      "Expression": {
                        "SourceRef": {
                          "Entity": "Date"
                        }
                      },
                      "Property": "Year"
                    }
                  },
                  "howCreated": 0
                },
                {
                  "name": "ec7fd8f6571bd4002386",
                  "type": "Advanced",
                  "filter": {
                    "Version": 2,
                    "From": [
                      {
                        "Name": "_",
                        "Entity": "_Measures",
                        "Type": 0
                      }
                    ],
                    "Where": [
                      {
                        "Condition": {
                          "Not": {
                            "Expression": {
                              "Comparison": {
                                "ComparisonKind": 0,
                                "Left": {
                                  "Measure": {
                                    "Expression": {
                                      "SourceRef": {
                                        "Source": "_"
                                      }
                                    },
                                    "Property": "VLF Filter - Instance status"
                                  }
                                },
                                "Right": {
                                  "Literal": {
                                    "Value": "null"
                                  }
                                }
                              }
                            }
                          }
                        }
                      }
                    ]
                  },
                  "expression": {
                    "Measure": {
                      "Expression": {
                        "SourceRef": {
                          "Entity": "_Measures"
                        }
                      },
                      "Property": "VLF Filter - Instance status"
                    }
                  },
                  "howCreated": 1
                }
              ]
            },
            "singleVisual": {
              "visualType": "slicer",
              "objects": {},
              "activeProjections": {
                "Values": [
                  {
                    "Column": {
                      "Expression": {
                        "SourceRef": {
                          "Entity": "Date"
                        }
                      },
                      "Property": "Year"
                    }
                  }
                ]
              }
            }
          },
          "324b4d54552e3e1a6520": {
            "singleVisual": {
              "visualType": "shape",
              "objects": {}
            }
          },
          "8bd44ad8b537661a0384": {
            "filters": {
              "byExpr": [
                {
                  "name": "f6dc5db57c93d3a273cc",
                  "type": "Advanced",
                  "expression": {
                    "Column": {
                      "Expression": {
                        "SourceRef": {
                          "Entity": "Date"
                        }
                      },
                      "Property": "Day index"
                    }
                  },
                  "howCreated": 0
                },
                {
                  "name": "387775f0521700ac1532",
                  "type": "Advanced",
                  "filter": {
                    "Version": 2,
                    "From": [
                      {
                        "Name": "_",
                        "Entity": "_Measures",
                        "Type": 0
                      }
                    ],
                    "Where": [
                      {
                        "Condition": {
                          "Not": {
                            "Expression": {
                              "Comparison": {
                                "ComparisonKind": 0,
                                "Left": {
                                  "Measure": {
                                    "Expression": {
                                      "SourceRef": {
                                        "Source": "_"
                                      }
                                    },
                                    "Property": "VLF Filter - Instance status"
                                  }
                                },
                                "Right": {
                                  "Literal": {
                                    "Value": "null"
                                  }
                                }
                              }
                            }
                          }
                        }
                      }
                    ]
                  },
                  "expression": {
                    "Measure": {
                      "Expression": {
                        "SourceRef": {
                          "Entity": "_Measures"
                        }
                      },
                      "Property": "VLF Filter - Instance status"
                    }
                  },
                  "howCreated": 1
                }
              ]
            },
            "singleVisual": {
              "visualType": "slicer",
              "objects": {},
              "activeProjections": {
                "Values": [
                  {
                    "Column": {
                      "Expression": {
                        "SourceRef": {
                          "Entity": "Date"
                        }
                      },
                      "Property": "Day index"
                    }
                  }
                ]
              }
            }
          },
          "e28d7322462dd06240eb": {
            "singleVisual": {
              "visualType": "shape",
              "objects": {}
            }
          },
          "86e8f2d1195b046408c9": {
            "filters": {
              "byExpr": [
                {
                  "name": "1d0176d2a22e446218e6",
                  "type": "Advanced",
                  "expression": {
                    "Measure": {
                      "Expression": {
                        "SourceRef": {
                          "Entity": "_Measures"
                        }
                      },
                      "Property": "Show filters Headers - Instance status"
                    }
                  },
                  "howCreated": 0
                },
                {
                  "name": "de9e9e50202cacac1ec0",
                  "type": "Advanced",
                  "expression": {
                    "Measure": {
                      "Expression": {
                        "SourceRef": {
                          "Entity": "_Measures"
                        }
                      },
                      "Property": "Show filters - Instance status"
                    }
                  },
                  "howCreated": 0
                }
              ]
            },
            "singleVisual": {
              "visualType": "tableEx",
              "objects": {}
            }
          },
          "8a86d81f68eb8828c787": {
            "filters": {
              "byExpr": [
                {
                  "name": "6782e79b7833604bb26a",
                  "type": "Advanced",
                  "expression": {
                    "Column": {
                      "Expression": {
                        "SourceRef": {
                          "Entity": "Date"
                        }
                      },
                      "Property": "Day"
                    }
                  },
                  "howCreated": 0
                },
                {
                  "name": "446a1bed027000d59994",
                  "type": "Advanced",
                  "filter": {
                    "Version": 2,
                    "From": [
                      {
                        "Name": "_",
                        "Entity": "_Measures",
                        "Type": 0
                      }
                    ],
                    "Where": [
                      {
                        "Condition": {
                          "Not": {
                            "Expression": {
                              "Comparison": {
                                "ComparisonKind": 0,
                                "Left": {
                                  "Measure": {
                                    "Expression": {
                                      "SourceRef": {
                                        "Source": "_"
                                      }
                                    },
                                    "Property": "VLF Filter - Instance status"
                                  }
                                },
                                "Right": {
                                  "Literal": {
                                    "Value": "null"
                                  }
                                }
                              }
                            }
                          }
                        }
                      }
                    ]
                  },
                  "expression": {
                    "Measure": {
                      "Expression": {
                        "SourceRef": {
                          "Entity": "_Measures"
                        }
                      },
                      "Property": "VLF Filter - Instance status"
                    }
                  },
                  "howCreated": 1
                }
              ]
            },
            "singleVisual": {
              "visualType": "slicer",
              "objects": {},
              "activeProjections": {
                "Values": [
                  {
                    "Column": {
                      "Expression": {
                        "SourceRef": {
                          "Entity": "Date"
                        }
                      },
                      "Property": "Day"
                    }
                  }
                ]
              }
            }
          },
          "b2f3dc15270ca2651135": {
            "filters": {
              "byExpr": [
                {
                  "name": "5c6934e700be5ba6cad9",
                  "type": "Categorical",
                  "expression": {
                    "Column": {
                      "Expression": {
                        "SourceRef": {
                          "Entity": "Date"
                        }
                      },
                      "Property": "Month"
                    }
                  },
                  "howCreated": 0
                },
                {
                  "name": "931674ac204ab75002a5",
                  "type": "Advanced",
                  "filter": {
                    "Version": 2,
                    "From": [
                      {
                        "Name": "_",
                        "Entity": "_Measures",
                        "Type": 0
                      }
                    ],
                    "Where": [
                      {
                        "Condition": {
                          "Not": {
                            "Expression": {
                              "Comparison": {
                                "ComparisonKind": 0,
                                "Left": {
                                  "Measure": {
                                    "Expression": {
                                      "SourceRef": {
                                        "Source": "_"
                                      }
                                    },
                                    "Property": "VLF Filter - Instance status"
                                  }
                                },
                                "Right": {
                                  "Literal": {
                                    "Value": "null"
                                  }
                                }
                              }
                            }
                          }
                        }
                      }
                    ]
                  },
                  "expression": {
                    "Measure": {
                      "Expression": {
                        "SourceRef": {
                          "Entity": "_Measures"
                        }
                      },
                      "Property": "VLF Filter - Instance status"
                    }
                  },
                  "howCreated": 1
                }
              ]
            },
            "singleVisual": {
              "visualType": "slicer",
              "objects": {},
              "activeProjections": {
                "Values": [
                  {
                    "Column": {
                      "Expression": {
                        "SourceRef": {
                          "Entity": "Date"
                        }
                      },
                      "Property": "Month"
                    }
                  }
                ]
              }
            }
          },
          "69662287741d0dd50bb0": {
            "singleVisual": {
              "visualType": "actionButton",
              "objects": {}
            }
          },
          "1a8a2deee0069a30e2b6": {
            "filters": {
              "byExpr": [
                {
                  "name": "ef2bb9fde68039493488",
                  "type": "Advanced",
                  "expression": {
                    "Measure": {
                      "Expression": {
                        "SourceRef": {
                          "Entity": "_Measures"
                        }
                      },
                      "Property": "Open filter button tooltip - Instance status"
                    }
                  },
                  "howCreated": 0
                }
              ]
            },
            "singleVisual": {
              "visualType": "card",
              "objects": {}
            }
          }
        },
        "visualContainerGroups": {
          "046cbda50e6c2907e052": {
            "isHidden": false
          },
          "037dbe7e00733d80c1b2": {
            "isHidden": true
          }
        }
      }
    },
    "objects": {
      "merge": {
        "outspacePane": [
          {
            "properties": {
              "expanded": {
                "expr": {
                  "Literal": {
                    "Value": "true"
                  }
                }
              }
            }
          }
        ]
      }
    }
  }
}